AUTHORS
CHANGES
LICENSE
MANIFEST.in
Makefile
setup.cfg
setup.py
tox.ini
git_deploy/__init__.py
git_deploy/config.py
git_deploy/git_deploy.py
git_deploy/git_methods.py
git_deploy/utils.py
git_deploy.egg-info/PKG-INFO
git_deploy.egg-info/SOURCES.txt
git_deploy.egg-info/dependency_links.txt
git_deploy.egg-info/entry_points.txt
git_deploy.egg-info/not-zip-safe
git_deploy.egg-info/requires.txt
git_deploy.egg-info/top_level.txt