Metadata-Version: 1.0
Name: git-deploy
Version: 0.3.0dev-20140209
Summary: Tool to manage using git as a deployment management tool
Home-page: https://github.com/Git-Tools/git-deploy
Author: Git Tools
Author-email: preilly@php.net,bobs.ur.uncle@gmail.com
License: License :: OSI Approved :: BSD License
Keywords: git,deploy,scripts,cli
Platform: UNKNOWN
Classifier: Development Status :: 4 - Beta
Classifier: Environment :: Console
Classifier: Intended Audience :: Developers
Classifier: Topic :: Utilities
Classifier: Topic :: Software Development :: Version Control
Classifier: Programming Language :: Python
Classifier: Programming Language :: Python :: 2.7
Classifier: Operating System :: OS Independent
Classifier: License :: OSI Approved :: BSD License
Classifier: License :: OSI Approved :: MIT License
